dev_up/__init__.py
dev_up/abc/__init__.py
dev_up/abc/api.py
dev_up/abc/category.py
dev_up/abc/json.py
dev_up/abc/models.py
dev_up/abc/session.py
dev_up/api.py
dev_up/base/__init__.py
dev_up/base/category.py
dev_up/base/json.py
dev_up/base/models.py
dev_up/base/protocols.py
dev_up/base/session.py
dev_up/categories/__init__.py
dev_up/categories/api.py
dev_up/categories/audio.py
dev_up/categories/profile.py
dev_up/categories/utils.py
dev_up/categories/vk.py
dev_up/exceptions.py
dev_up/models/__init__.py
dev_up/models/request/__init__.py
dev_up/models/request/audio/__init__.py
dev_up/models/request/audio/speech.py
dev_up/models/request/profile/__init__.py
dev_up/models/request/profile/buy_limit.py
dev_up/models/request/profile/buy_premium.py
dev_up/models/request/profile/get.py
dev_up/models/request/profile/get_balance_link.py
dev_up/models/request/profile/set_key.py
dev_up/models/request/utils/__init__.py
dev_up/models/request/utils/check_link.py
dev_up/models/request/utils/create_short_link.py
dev_up/models/request/utils/get_server_time.py
dev_up/models/request/utils/get_web_info.py
dev_up/models/request/utils/md5_generate.py
dev_up/models/request/utils/notifications_links.py
dev_up/models/request/vk/__init__.py
dev_up/models/request/vk/experts_get_info.py
dev_up/models/request/vk/get_apps.py
dev_up/models/request/vk/get_groups.py
dev_up/models/request/vk/get_sticker_info.py
dev_up/models/request/vk/get_stickers.py
dev_up/models/request/vk/group_get_managers.py
dev_up/models/request/vk/search_audio.py
dev_up/models/request/vk/search_playlists.py
dev_up/models/request/vk/set_steps.py
dev_up/models/request/vk/testers_get_info.py
dev_up/models/request/vk/user_get_subscriptions.py
dev_up/models/response/__init__.py
dev_up/models/response/audio/__init__.py
dev_up/models/response/audio/speech.py
dev_up/models/response/profile/__init__.py
dev_up/models/response/profile/buy_limit.py
dev_up/models/response/profile/buy_premium.py
dev_up/models/response/profile/get.py
dev_up-2.0.0.dist-info/LICENSE
dev_up-2.0.0.dist-info/WHEEL
dev_up-2.0.0.dist-info/METADATA
dev_up-2.0.0.dist-info/RECORD
